robotaxi/__init__.py
robotaxi/module.py
text2video/__init__.py
text2video/module.py
virtual-world/__init__.py
virtual-world/module.py
virtual-worlds/__init__.py
virtual-worlds/module.py
virtual_worlds-0.0.1.dist-info/METADATA
virtual_worlds-0.0.1.dist-info/WHEEL
virtual_worlds-0.0.1.dist-info/top_level.txt
virtual_worlds-0.0.1.dist-info/RECORD
